pylicense3/__init__.py
pylicense3/_version.py
pylicense3/cli.py
pylicense3-0.5.0.dist-info/AUTHORS.md
pylicense3-0.5.0.dist-info/LICENSE
pylicense3-0.5.0.dist-info/METADATA
pylicense3-0.5.0.dist-info/WHEEL
pylicense3-0.5.0.dist-info/entry_points.txt
pylicense3-0.5.0.dist-info/top_level.txt
pylicense3-0.5.0.dist-info/RECORD
